{
  "songs": [
    {
      "id": "2",
      "name": "Ngày mai là tương lai",
      "img": "https://i.ytimg.com/vi/Wi-_jZ8Spbc/maxresdefault.jpg",
      "audioSong": "sound/y2mate.com - NGÀY MAI LÀ TƯƠNG LAI feat Obito.mp3",
      "singer": "obito otđ",
      "time": "2:30"
    },
    {
      "id": "3",
      "name": "Chỉ một đêm nữa thôi",
      "img": "https://encrypted-tbn0.gstatic.com/images?q=tbn:ANd9GcSktyowSM9Ca4YG5Mm8mC9jzw5B4X9pJTne1A&s",
      "audioSong": "sound/y2mate.com - MCK TLINH  CHỈ MỘT ĐÊM NỮA THÔI   LIVE BUJI CLUB by 8849Studio .mp3",
      "singer": "t linh ft mck",
      "time": "3:20"
    },
    {
      "id": "4",
      "name": "Lạc trôi",
      "img": "https://i.scdn.co/image/ab67616d0000b27342ea0500b59064819d1c07fa",
      "audioSong": "sound/y2mate.com - LẠC TRÔI  OFFICIAL MUSIC VIDEO  SƠN TÙNG MTP_360p.mp4",
      "singer": "son tung mtp",
      "time": "3:15"
    },
    {
      "id": "5",
      "name": "Hà nội",
      "img": "https://i.scdn.co/image/ab67616d0000b2730ecdf596e76b0403506c1375",
      "audioSong": "sound/y2mate.com - Obito  Hà Nội ft VSTRA.mp3",
      "singer": "obito otđ",
      "time": "3:10"
    },
    {
      "id": "6",
      "name": "Chúng ta của tương lai",
      "img": "https://encrypted-tbn0.gstatic.com/images?q=tbn:ANd9GcT4G2hNUOJMCAn2AK3ODgpNDdXw5ZEszxzUGQ&s",
      "audioSong": "sound/y2mate.com - SƠN TÙNG MTP  CHÚNG TA CỦA TƯƠNG LAI  OFFICIAL MUSIC VIDEO_360p.mp4",
      "singer": "son tung mtp",
      "time": "4:10"
    },
    {
      "id": "7",
      "name": "Vài câu nói",
      "img": "https://i.scdn.co/image/ab67616d0000b273e539f5611166930d7d9f6297",
      "audioSong": "sound/y2mate.com - GREY D x tlinh  vaicaunoicokhiennguoithaydoi  Official Music Video.mp3",
      "singer": "GreyD ft tlinh",
      "time": "2:10"
    },
    {
      "id": "8",
      "name": "Đánh đổi",
      "img": "https://i.scdn.co/image/ab6761610000e5eba385bd3e0f67945f277792c2",
      "audioSong": "sound/y2mate.com - Obito  Đánh Đổi ft MCK.mp3",
      "singer": "obito otđ",
      "time": "2:45"
    },
    {
      "id": "9",
      "name": "Free from desire",
      "img": "https://i.scdn.co/image/ab67616d0000b273892bd2e54011c2a7549af570",
      "audioSong": "sound/y2mate.com - Freed From Desire Lyrics  Drenchill Indiiana.mp3",
      "singer": "drenchill ft indiiana",
      "time": "3:20"
    }
  ]
}